igcs/__init__.py
igcs/configs.py
igcs/cseval.py
igcs/entities.py
igcs/predict.py
igcs/datasets/__init__.py
igcs/datasets/prepare_igcs_datasets.py
igcs/datasets/create_gencs_dataset/__init__.py
igcs/datasets/create_gencs_dataset/annotate_dataset.py
igcs/datasets/create_gencs_dataset/annotate_dataset_single_step.py
igcs/datasets/create_gencs_dataset/create_reverse_instructions_dataset_splits.py
igcs/datasets/create_gencs_dataset/make_dataset_e2e.py
igcs/datasets/create_gencs_dataset/response_parser.py
igcs/datasets/create_gencs_dataset/sample_datasets_for_tagging.py
igcs/datasets/create_gencs_dataset/prepare_sources/__init__.py
igcs/datasets/create_gencs_dataset/prepare_sources/enron_emails.py
igcs/datasets/create_gencs_dataset/prepare_sources/github_code.py
igcs/datasets/create_gencs_dataset/prepare_sources/pg19_books.py
igcs/datasets/create_gencs_dataset/prepare_sources/pubmed_abstracts.py
igcs/datasets/create_gencs_dataset/prepare_sources/tripadvisor_reviews.py
igcs/datasets/create_gencs_dataset/prepare_sources/wiki_pages.py
igcs/datasets/igcsbench_datasets/__init__.py
igcs/datasets/igcsbench_datasets/aspectnews.py
igcs/datasets/igcsbench_datasets/base.py
igcs/datasets/igcsbench_datasets/debatesum.py
igcs/datasets/igcsbench_datasets/openasp.py
igcs/datasets/igcsbench_datasets/reverse_instructions.py
igcs/datasets/igcsbench_datasets/scifact.py
igcs/datasets/igcsbench_datasets/spark.py
igcs/evaluate/__init__.py
igcs/evaluate/evaluation_functions.py
igcs/evaluate/helpers.py
igcs/evaluate/ila.py
igcs/evaluate/external/__init__.py
igcs/evaluate/external/aspectnews_evaluate.py
igcs/evaluate/external/convert_to_scifact_format.py
igcs/evaluate/external/helper.py
igcs/evaluate/external/openasp_eval.py
igcs/evaluate/external/scifact_rationale_selection.py
igcs/grounding/__init__.py
igcs/grounding/completion_parsers.py
igcs/grounding/selection_utils.py
igcs/grounding/tokenization.py
igcs/llms/__init__.py
igcs/llms/claude.py
igcs/llms/gemini.py
igcs/llms/gpt4.py
igcs-0.0.2.dist-info/licenses/LICENSE-APACHE
igcs-0.0.2.dist-info/licenses/LICENSE-MIT
igcs-0.0.2.dist-info/METADATA
igcs-0.0.2.dist-info/WHEEL
igcs-0.0.2.dist-info/top_level.txt
igcs-0.0.2.dist-info/RECORD
