Metadata-Version: 2.4
Name: igcs
Version: 0.0.2
Summary: Instruction‑Guided Content Selection toolkit and datasets
Author: Shmuel Amar
Maintainer: Shmuel Amar
License-Expression: Apache-2.0 OR MIT
Project-URL: Homepage, https://github.com/shmuelamar/igcs
Project-URL: Bug Tracker, https://github.com/shmuelamar/igcs/issues
Project-URL: Source, https://github.com/shmuelamar/igcs
Keywords: instruction‑guided,content‑selection,extractive‑summarisation,evidence‑extraction,benchmark,LLM,transfer‑learning,NLP
Classifier: Development Status :: 4 - Beta
Classifier: Intended Audience :: Developers
Classifier: Intended Audience :: Science/Research
Classifier: Topic :: Scientific/Engineering :: Artificial Intelligence
Classifier: Topic :: Text Processing :: Linguistic
Classifier: Topic :: Software Development :: Libraries :: Python Modules
Classifier: Operating System :: OS Independent
Classifier: Programming Language :: Python :: 3
Classifier: Programming Language :: Python :: 3.11
Classifier: Programming Language :: Python :: 3.12
Classifier: Programming Language :: Python :: 3.13
Classifier: Programming Language :: Python :: 3 :: Only
Requires-Python: >=3.9
License-File: LICENSE-APACHE
License-File: LICENSE-MIT
Requires-Dist: fuzzysearch<1,>=0.7.3
Requires-Dist: pydantic<3,>=2.6.4
Requires-Dist: spacy<3.8,>=3.7.2
Provides-Extra: train
Requires-Dist: anthropic==0.25.6; extra == "train"
Requires-Dist: pydantic==2.6.4; extra == "train"
Requires-Dist: nltk==3.8.1; extra == "train"
Requires-Dist: numpy==1.26.4; extra == "train"
Requires-Dist: scipy==1.12.0; extra == "train"
Requires-Dist: rich==13.7.1; extra == "train"
Requires-Dist: pandas==2.2.2; extra == "train"
Requires-Dist: xmltodict==0.13.0; extra == "train"
Requires-Dist: openai==1.23.4; extra == "train"
Requires-Dist: spacy==3.7.4; extra == "train"
Requires-Dist: markdown-to-json==2.1.0; extra == "train"
Requires-Dist: fuzzysearch==0.7.3; extra == "train"
Requires-Dist: google-generativeai==0.5.2; extra == "train"
Requires-Dist: scikit-learn==1.4.2; extra == "train"
Requires-Dist: transformers==4.41.2; extra == "train"
Requires-Dist: tiktoken==0.7.0; extra == "train"
Requires-Dist: accelerate==0.30.0; extra == "train"
Requires-Dist: datasets==2.19.1; extra == "train"
Requires-Dist: beautifulsoup4==4.9.3; extra == "train"
Requires-Dist: openpyxl==3.1.3; extra == "train"
Requires-Dist: rouge-score==0.1.2; extra == "train"
Requires-Dist: deepspeed==0.15.0; extra == "train"
Requires-Dist: peft==0.12.0; extra == "train"
Requires-Dist: trl==0.10.1; extra == "train"
Requires-Dist: flash-attn==2.6.3; extra == "train"
Requires-Dist: wandb==0.17.8; extra == "train"
Requires-Dist: jsonlines==4.0.0; extra == "train"
Requires-Dist: together==1.2.12; extra == "train"
Requires-Dist: gradio==4.26.0; extra == "train"
Provides-Extra: develop
Requires-Dist: anthropic==0.25.6; extra == "develop"
Requires-Dist: pydantic==2.6.4; extra == "develop"
Requires-Dist: nltk==3.8.1; extra == "develop"
Requires-Dist: numpy==1.26.4; extra == "develop"
Requires-Dist: scipy==1.12.0; extra == "develop"
Requires-Dist: rich==13.7.1; extra == "develop"
Requires-Dist: pandas==2.2.2; extra == "develop"
Requires-Dist: xmltodict==0.13.0; extra == "develop"
Requires-Dist: openai==1.23.4; extra == "develop"
Requires-Dist: spacy==3.7.4; extra == "develop"
Requires-Dist: markdown-to-json==2.1.0; extra == "develop"
Requires-Dist: fuzzysearch==0.7.3; extra == "develop"
Requires-Dist: google-generativeai==0.5.2; extra == "develop"
Requires-Dist: scikit-learn==1.4.2; extra == "develop"
Requires-Dist: transformers==4.41.2; extra == "develop"
Requires-Dist: tiktoken==0.7.0; extra == "develop"
Requires-Dist: accelerate==0.30.0; extra == "develop"
Requires-Dist: datasets==2.19.1; extra == "develop"
Requires-Dist: beautifulsoup4==4.9.3; extra == "develop"
Requires-Dist: openpyxl==3.1.3; extra == "develop"
Requires-Dist: rouge-score==0.1.2; extra == "develop"
Requires-Dist: deepspeed==0.15.0; extra == "develop"
Requires-Dist: peft==0.12.0; extra == "develop"
Requires-Dist: trl==0.10.1; extra == "develop"
Requires-Dist: flash-attn==2.6.3; extra == "develop"
Requires-Dist: wandb==0.17.8; extra == "develop"
Requires-Dist: jsonlines==4.0.0; extra == "develop"
Requires-Dist: together==1.2.12; extra == "develop"
Requires-Dist: gradio==4.26.0; extra == "develop"
Dynamic: license-file
